worker/__init__.py
worker/main.py
worker/utils.py
worker/cmd/__init__.py
worker/cmd/hello.py
worker/cmd/join.py
worker/cmd/serve.py
worker/server/__init__.py
worker/server/server.py
Ocean_Agent_Worker-0.0.5.dist-info/METADATA
Ocean_Agent_Worker-0.0.5.dist-info/WHEEL
Ocean_Agent_Worker-0.0.5.dist-info/entry_points.txt
Ocean_Agent_Worker-0.0.5.dist-info/top_level.txt
Ocean_Agent_Worker-0.0.5.dist-info/RECORD
