Metadata-Version: 2.1
Name: Ocean-Agent-Worker
Version: 0.0.5
Summary: Ocean-Agent for Worker nodes
Home-page: UNKNOWN
Author: kairos03
Author-email: kairos9603@gmail.com
License: UNKNOWN
Platform: UNKNOWN
Requires-Dist: websockets
Requires-Dist: click
Requires-Dist: requests
Requires-Dist: flask
Requires-Dist: APScheduler
Requires-Dist: dnspython
